asyncbolt/__init__.py
asyncbolt/buffer.py
asyncbolt/client.py
asyncbolt/exception.py
asyncbolt/messaging.py
asyncbolt/parser.py
asyncbolt/protocol.py
asyncbolt/server.py
asyncbolt-0.0.2.dist-info/DESCRIPTION.rst
asyncbolt-0.0.2.dist-info/METADATA
asyncbolt-0.0.2.dist-info/RECORD
asyncbolt-0.0.2.dist-info/WHEEL
asyncbolt-0.0.2.dist-info/metadata.json
asyncbolt-0.0.2.dist-info/top_level.txt
